cachine/__init__.py
cachine/backends/__init__.py
cachine/backends/inmemory/__init__.py
cachine/backends/inmemory/cache.py
cachine/backends/redis/__init__.py
cachine/backends/redis/async_.py
cachine/backends/redis/pubsub.py
cachine/backends/redis/scripts/counters.lua
cachine/backends/redis/scripts/invalidate_tags.lua
cachine/backends/redis/scripts/unlock.lua
cachine/backends/redis/sync.py
cachine/builder.py
cachine/core/__init__.py
cachine/core/types.py
cachine/decorators/__init__.py
cachine/decorators/_utils.py
cachine/decorators/cached.py
cachine/exceptions.py
cachine/factory.py
cachine/middleware/__init__.py
cachine/middleware/base.py
cachine/middleware/compression.py
cachine/middleware/encryption.py
cachine/middleware/fail_open.py
cachine/middleware/metrics.py
cachine/models/__init__.py
cachine/models/common.py
cachine/models/redis_config.py
cachine/py.typed
cachine/serializers/__init__.py
cachine/serializers/base.py
cachine/serializers/json.py
cachine/serializers/msgpack.py
cachine/serializers/pickle.py
cachine/strategies/__init__.py
cachine/strategies/eviction.py
cachine/strategies/invalidation.py
cachine/types.py
cachine/utils/__init__.py
cachine/utils/helpers.py
cachine/utils/key_builder.py
cachine/utils/logging_utils.py
cachine/utils/redis_url.py
cachine-0.1.0.dist-info/METADATA
cachine-0.1.0.dist-info/WHEEL
cachine-0.1.0.dist-info/RECORD
