Metadata-Version: 2.3
Name: cachine
Version: 0.1.0
Summary: A powerful sync/async caching library for Python with tag-based invalidation and Redis backend.
License: MIT
Author: haonguyen
Author-email: vanhao1915@gmail.com
Requires-Python: >=3.10
Classifier: License :: OSI Approved :: MIT License
Classifier: Programming Language :: Python :: 3
Classifier: Programming Language :: Python :: 3.10
Classifier: Programming Language :: Python :: 3.11
Classifier: Programming Language :: Python :: 3.12
Classifier: Programming Language :: Python :: 3.13
Requires-Dist: colorama (>=0.4.6,<0.5.0)
Requires-Dist: redis (>=7.0.1,<8.0.0)
Project-URL: Homepage, https://github.com/haonguyen1915/cachine
Project-URL: PyPI, https://pypi.org/project/cachine/
Project-URL: Repository, https://github.com/haonguyen1915/cachine
